segmetrics/__init__.py
SegKit-0.0.1.dist-info/LICENSE
SegKit-0.0.1.dist-info/METADATA
SegKit-0.0.1.dist-info/WHEEL
SegKit-0.0.1.dist-info/top_level.txt
SegKit-0.0.1.dist-info/RECORD
